gitlabapi
