Metadata-Version: 1.1
Name: gitlab-cli
Version: 0.0.2
Summary: CLI interface for gitlab
Home-page: https://github.com/oskyk/gitlab-cli
Author: Oskar Hladky
Author-email: oskyks1@gmail.com
License: UNKNOWN
Download-URL: https://github.com/oskyk/gitlab-cli/archive/0.0.1.tar.gz
Keywords: gitlab,cli
Platform: UNKNOWN
